msgraph/__init__.py
msgraph/_version.py
msgraph/graph_request_adapter.py
msgraph/graph_service_client.py
msgraph_beta_sdk-1.0.0a8.dist-info/LICENSE
msgraph_beta_sdk-1.0.0a8.dist-info/METADATA
msgraph_beta_sdk-1.0.0a8.dist-info/WHEEL
msgraph_beta_sdk-1.0.0a8.dist-info/top_level.txt
msgraph_beta_sdk-1.0.0a8.dist-info/RECORD
