Metadata-Version: 2.1
Name: msgraph-beta-sdk
Version: 1.0.0a8
Summary: The Microsoft Graph Beta Python SDK
Author-email: Microsoft <graphtooling+python@microsoft.com>
License: MIT License
Project-URL: homepage, https://github.com/microsoftgraph/msgraph-beta-sdk-python#readme
Project-URL: repository, https://github.com/microsoftgraph/msgraph-beta-sdk-python
Project-URL: documentation, https://github.com/microsoftgraph/msgraph-beta-sdk-python/docs
Keywords: msgraph,openAPI,Microsoft,Graph,beta
Classifier: Development Status :: 3 - Alpha
Classifier: Programming Language :: Python :: 3.6
Classifier: Programming Language :: Python :: 3.7
Classifier: Programming Language :: Python :: 3.8
Classifier: Programming Language :: Python :: 3.9
Classifier: Programming Language :: Python :: 3.10
Classifier: Programming Language :: Python :: 3.11
Classifier: License :: OSI Approved :: MIT License
Requires-Python: >=3.6
License-File: LICENSE
Requires-Dist: azure-identity (>=1.10.0)
Requires-Dist: microsoft-kiota-abstractions (>=0.5.0)
Requires-Dist: microsoft-kiota-authentication-azure (>=0.2.0)
Requires-Dist: microsoft-kiota-serialization-json (>=0.3.0)
Requires-Dist: microsoft-kiota-serialization-text (>=0.2.0)
Requires-Dist: msgraph-core (>=1.0.0a2)
Provides-Extra: dev
Requires-Dist: yapf ; extra == 'dev'
Requires-Dist: bumpver ; extra == 'dev'
Requires-Dist: isort ; extra == 'dev'
Requires-Dist: pylint ; extra == 'dev'
Requires-Dist: pytest ; extra == 'dev'
Requires-Dist: mypy ; extra == 'dev'
